LICENSE
LICENSE.txt
README.rst
setup.cfg
setup.py
mynameissaichon/__init__.py
mynameissaichon/saichon.py
mynameissaichon.egg-info/PKG-INFO
mynameissaichon.egg-info/SOURCES.txt
mynameissaichon.egg-info/dependency_links.txt
mynameissaichon.egg-info/top_level.txt