Metadata-Version: 2.1
Name: mynameissaichon
Version: 0.1.1
Summary: Who is Saichon?
Home-page: https://github.com/chindo33/mynameissaichon
Download-URL: https://github.com/chindo33/mynameissaichon
Author: Saichon
Author-email: chindo.minras@gmail.com
License: MIT
Keywords: Saichon,ASCII ART
Classifier: Development Status :: 3 - Alpha
Classifier: Intended Audience :: Education
Classifier: Topic :: Utilities
Classifier: License :: OSI Approved :: MIT License
Classifier: Programming Language :: Python :: 3
Classifier: Programming Language :: Python :: 3.4
Classifier: Programming Language :: Python :: 3.5
Classifier: Programming Language :: Python :: 3.6
Classifier: Programming Language :: Python :: 3.7
Classifier: Programming Language :: Python :: 3.8
Classifier: Programming Language :: Python :: 3.9
Classifier: Programming Language :: Python :: 3.10
License-File: LICENSE
License-File: LICENSE.txt
